gguf_selector/__init__.py
gguf_selector/connector.py
gguf_selector/logo.png
gguf_selector-0.0.5.dist-info/LICENSE
gguf_selector-0.0.5.dist-info/WHEEL
gguf_selector-0.0.5.dist-info/METADATA
gguf_selector-0.0.5.dist-info/RECORD
