Metadata-Version: 2.1
Name: gguf-selector
Version: 0.0.5
Summary: GGUF selector
Author-email: calcuis <info@calcu.io>
Classifier: Development Status :: 4 - Beta
Classifier: Intended Audience :: Developers
Classifier: Intended Audience :: Education
Classifier: Intended Audience :: Science/Research
Classifier: License :: OSI Approved :: MIT License
Classifier: Programming Language :: Python :: 3
Classifier: Topic :: Scientific/Engineering :: Artificial Intelligence
Classifier: Topic :: Scientific/Engineering :: Mathematics
Classifier: Topic :: Software Development :: Libraries :: Python Modules
Requires-Dist: llama-core >=0.1.2
Project-URL: Homepage, https://github.com/calcuis/gguf-selector
Project-URL: Issues, https://github.com/calcuis/gguf-selector/issues
